leanai/__init__.py
leanai/core/__init__.py
leanai/core/annotations.py
leanai/core/capture_tensors.py
leanai/core/config.py
leanai/core/definitions.py
leanai/core/experiment.py
leanai/core/indexed_tensor_helpers.py
leanai/core/logging.py
leanai/core/tensorboard.py
leanai/data/__init__.py
leanai/data/data_promise.py
leanai/data/dataloader.py
leanai/data/dataset.py
leanai/data/file_provider.py
leanai/data/parser.py
leanai/data/serializer.py
leanai/data/transform.py
leanai/data/datasets/__init__.py
leanai/data/datasets/casia_faces.py
leanai/data/datasets/coco.py
leanai/data/datasets/fashion_mnist.py
leanai/data/datasets/images_in_classfolders.py
leanai/data/datasets/kitti_object.py
leanai/data/datasets/kitti_object_splits.py
leanai/data/datasets/nuimages.py
leanai/data/datasets/nuscenes.py
leanai/data/datasets/pickled.py
leanai/data/datasets/webdataset.py
leanai/data/transforms/__init__.py
leanai/data/transforms/bounding_boxes.py
leanai/data/transforms/image.py
leanai/data/visualizations/__init__.py
leanai/data/visualizations/plot_boxes.py
leanai/model/__init__.py
leanai/model/configs/__init__.py
leanai/model/configs/fasterrcnn.py
leanai/model/configs/simple_classifier.py
leanai/model/layers/__init__.py
leanai/model/layers/activation.py
leanai/model/layers/batch_normalization.py
leanai/model/layers/convolution.py
leanai/model/layers/dense.py
leanai/model/layers/detection.py
leanai/model/layers/dropout.py
leanai/model/layers/flatten.py
leanai/model/layers/image_conversion.py
leanai/model/layers/parallel.py
leanai/model/layers/pooling.py
leanai/model/layers/reshape.py
leanai/model/layers/roi_ops.py
leanai/model/layers/selection.py
leanai/model/layers/sequential.py
leanai/model/layers/tensor_combiners.py
leanai/model/modules/__init__.py
leanai/model/modules/backbones.py
leanai/model/modules/classifierhead.py
leanai/model/modules/detector.py
leanai/training/__init__.py
leanai/training/losses/__init__.py
leanai/training/losses/classification.py
leanai-2.3.0.dist-info/LICENSE
leanai-2.3.0.dist-info/METADATA
leanai-2.3.0.dist-info/WHEEL
leanai-2.3.0.dist-info/top_level.txt
leanai-2.3.0.dist-info/RECORD
