Metadata-Version: 2.1
Name: leanai
Version: 2.3.0
Summary: A library to help writing ai functions with ease.
Home-page: https://github.com/penguinmenac3/leanai
Download-URL: https://github.com/penguinmenac3/leanai/tarball/2.3.0
Author: Michael Fuerst
Author-email: mail@michaelfuerst.de
License: MIT
Classifier: Development Status :: 3 - Alpha
Classifier: Intended Audience :: Developers
Classifier: Programming Language :: Python
License-File: LICENSE
Requires-Dist: numpy
Requires-Dist: imageio
Requires-Dist: jstyleson
Requires-Dist: torch
Requires-Dist: torchvision
Requires-Dist: GPUtil
Requires-Dist: psutil
Requires-Dist: pytorch-lightning
Requires-Dist: opencv-contrib-python
Requires-Dist: matplotlib
Requires-Dist: torchviz
Requires-Dist: torchsummary
Requires-Dist: webdataset
Requires-Dist: nuscenes-devkit
Requires-Dist: tf3d
Provides-Extra: all
Requires-Dist: open3d (==0.9.0.0) ; extra == 'all'
Requires-Dist: tensorboard ; extra == 'all'
Requires-Dist: nose2 ; extra == 'all'
Requires-Dist: packaging ; extra == 'all'
Provides-Extra: dev
Requires-Dist: nose2 ; extra == 'dev'
Requires-Dist: packaging ; extra == 'dev'
Provides-Extra: visualization
Requires-Dist: open3d (==0.9.0.0) ; extra == 'visualization'
Requires-Dist: tensorboard ; extra == 'visualization'
